encore/__init__.py
encore/concurrent/__init__.py
encore/concurrent/threadtools.py
encore/concurrent/futures/__init__.py
encore/concurrent/futures/abc_work_scheduler.py
encore/concurrent/futures/asynchronizer.py
encore/concurrent/futures/delayed_asynchronizer.py
encore/concurrent/futures/enhanced_thread_pool_executor.py
encore/concurrent/futures/future.py
encore/concurrent/futures/serializer.py
encore/concurrent/futures/serializing_asynchronizer.py
encore/concurrent/futures/synchronous.py
encore/concurrent/futures/tests/__init__.py
encore/concurrent/futures/tests/test_asynchronizer.py
encore/concurrent/futures/tests/test_delayed_asynchronizer.py
encore/concurrent/futures/tests/test_enhanced_thread_pool_executor.py
encore/concurrent/futures/tests/test_serializer.py
encore/concurrent/futures/tests/test_serializing_asynchronizer.py
encore/concurrent/futures/tests/test_synchronous_executor.py
encore/concurrent/tests/__init__.py
encore/concurrent/tests/test_threadtools.py
encore/events/__init__.py
encore/events/abstract_event_manager.py
encore/events/api.py
encore/events/event_manager.py
encore/events/heartbeat.py
encore/events/package_globals.py
encore/events/progress_events.py
encore/events/tests/__init__.py
encore/events/tests/test_event_manager.py
encore/storage/__init__.py
encore/storage/abstract_store.py
encore/storage/dict_memory_store.py
encore/storage/dynamic_url_store.py
encore/storage/events.py
encore/storage/file_lock.py
encore/storage/file_value.py
encore/storage/filesystem_store.py
encore/storage/joined_store.py
encore/storage/locking_filesystem_store.py
encore/storage/mounted_store.py
encore/storage/simple_auth_store.py
encore/storage/sqlite_store.py
encore/storage/static_url_store.py
encore/storage/string_value.py
encore/storage/url_value.py
encore/storage/utils.py
encore/storage/tests/__init__.py
encore/storage/tests/abstract_test.py
encore/storage/tests/dict_memory_store_test.py
encore/storage/tests/dynamic_url_store_test.py
encore-0.8.0.dist-info/LICENSE.txt
encore-0.8.0.dist-info/METADATA
encore-0.8.0.dist-info/WHEEL
encore-0.8.0.dist-info/top_level.txt
encore-0.8.0.dist-info/RECORD
