Metadata-Version: 2.1
Name: encore
Version: 0.8.0
Summary: Low-level core modules for building Python applications
Home-page: http://docs.enthought.com/encore/
Download-URL: https://github.com/enthought/encore
Author: Enthought, Inc
Author-email: info@enthought.com
Requires-Python: >=3.6
License-File: LICENSE.txt
